btc_random/__init__.py
btc_random/btc.py
btc_random-0.0.dist-info/LICENCE
btc_random-0.0.dist-info/METADATA
btc_random-0.0.dist-info/WHEEL
btc_random-0.0.dist-info/top_level.txt
btc_random-0.0.dist-info/RECORD
